dotconfig_hub/__init__.py
dotconfig_hub/cli.py
dotconfig_hub/config.py
dotconfig_hub/diff.py
dotconfig_hub/project_config.py
dotconfig_hub/sync.py
dotconfig_hub-0.1.2.dist-info/licenses/LICENSE
dotconfig_hub-0.1.2.dist-info/METADATA
dotconfig_hub-0.1.2.dist-info/WHEEL
dotconfig_hub-0.1.2.dist-info/entry_points.txt
dotconfig_hub-0.1.2.dist-info/top_level.txt
dotconfig_hub-0.1.2.dist-info/RECORD
