Metadata-Version: 2.4
Name: dotconfig-hub
Version: 0.1.2
Summary: Central management and distribution tool for favorite dotfiles and configuration templates
Author-email: hasegama <40445443+hasegama@users.noreply.github.com>
License: MIT
Project-URL: Homepage, https://github.com/hasegama/dotconfig-hub
Keywords: dotfiles,configuration,sync,templates,development-tools
Classifier: Development Status :: 3 - Alpha
Classifier: Intended Audience :: Developers
Classifier: Operating System :: OS Independent
Classifier: Programming Language :: Python :: 3.11
Classifier: Programming Language :: Python :: 3.12
Classifier: Topic :: Software Development :: Build Tools
Classifier: Topic :: System :: Installation/Setup
Classifier: Topic :: Utilities
Requires-Python: >=3.8
License-File: LICENSE
Requires-Dist: click>=8.0
Requires-Dist: pyyaml>=6.0
Requires-Dist: rich>=13.0
Requires-Dist: gitpython>=3.1
Dynamic: license-file
